reposmith/__init__.py
reposmith/__main__.py
reposmith/ci_utils.py
reposmith/cli.py
reposmith/config_utils.py
reposmith/console.py
reposmith/env_manager.py
reposmith/file_utils.py
reposmith/gitignore_utils.py
reposmith/license_utils.py
reposmith/logging_utils.py
reposmith/main.py
reposmith/venv_utils.py
reposmith/vscode_utils.py
reposmith/commands/__init__.py
reposmith/commands/doctor_cmd.py
reposmith/commands/init_cmd.py
reposmith/core/__init__.py
reposmith/core/fs.py
reposmith/utils/__init__.py
reposmith/utils/deps.py
reposmith/utils/paths.py
reposmith_tol-0.4.3.dist-info/licenses/LICENSE
reposmith_tol-0.4.3.dist-info/METADATA
reposmith_tol-0.4.3.dist-info/WHEEL
reposmith_tol-0.4.3.dist-info/entry_points.txt
reposmith_tol-0.4.3.dist-info/top_level.txt
reposmith_tol-0.4.3.dist-info/RECORD
