Metadata-Version: 2.4
Name: reposmith-tol
Version: 0.4.3
Summary: Portable Python project bootstrapper with venv, uv, VS Code, and CI integration.
Author-email: Tamer Hamad Faour <info@tameronline.com>
License-Expression: MIT
Project-URL: Homepage, https://github.com/TamerOnLine/reposmith-init
Project-URL: Repository, https://github.com/TamerOnLine/reposmith-init
Project-URL: Issues, https://github.com/TamerOnLine/reposmith-init/issues
Project-URL: Documentation, https://tameronline.github.io/reposmith-init/
Project-URL: Sponsor, https://github.com/sponsors/TamerOnLine
Project-URL: Discussions, https://github.com/TamerOnLine/reposmith-init/discussions
Keywords: bootstrap,venv,uv,vscode,license,scaffold,cli,project-generator
Classifier: Development Status :: 5 - Production/Stable
Classifier: Environment :: Console
Classifier: Intended Audience :: Developers
Classifier: Programming Language :: Python :: 3
Classifier: Programming Language :: Python :: 3.12
Classifier: Programming Language :: Python :: 3.13
Classifier: Operating System :: OS Independent
Classifier: Topic :: Software Development :: Build Tools
Classifier: Topic :: Utilities
Requires-Python: >=3.12
License-File: LICENSE
Requires-Dist: python-dotenv>=1.1.1
Provides-Extra: dev
Requires-Dist: pytest>=8.0; extra == "dev"
Requires-Dist: coverage>=7.6; extra == "dev"
Requires-Dist: ruff>=0.6; extra == "dev"
Requires-Dist: black>=24.8; extra == "dev"
Provides-Extra: publish
Requires-Dist: build>=1.3.0; extra == "publish"
Requires-Dist: twine>=6.2.0; extra == "publish"
Dynamic: license-file
